{"Application":{"PType":2,"BasePath":"C:\\Users\\97953\\Desktop\\Wyj.Blog (1)\\5.5.0\\aspnet-core\\src\\Wyj.Blog.Application","ProjectName":"Wyj.Blog.Application","CodeTemplates":[]},"Application_Shared":null,"Core":{"PType":0,"BasePath":"C:\\Users\\97953\\Desktop\\Wyj.Blog (1)\\5.5.0\\aspnet-core\\src\\Wyj.Blog.Core","ProjectName":"Wyj.Blog.Core","CodeTemplates":[]},"Core_Shared":null,"EF":{"PType":1,"BasePath":"C:\\Users\\97953\\Desktop\\Wyj.Blog (1)\\5.5.0\\aspnet-core\\src\\Wyj.Blog.EntityFrameworkCore","ProjectName":"Wyj.Blog.EntityFrameworkCore","CodeTemplates":[]},"Tests":{"PType":3,"BasePath":"C:\\Users\\97953\\Desktop\\Wyj.Blog (1)\\5.5.0\\aspnet-core\\test\\Wyj.Blog.Tests","ProjectName":"Wyj.Blog.Tests","CodeTemplates":[]},"MVC":{"PType":4,"BasePath":"C:\\Users\\97953\\Desktop\\Wyj.Blog (1)\\5.5.0\\aspnet-core\\src\\Wyj.Blog.Web.Mvc","ProjectName":"Wyj.Blog.Web.Mvc","CodeTemplates":[]},"Host":{"PType":8,"BasePath":"C:\\Users\\97953\\Desktop\\Wyj.Blog (1)\\5.5.0\\aspnet-core\\src\\Wyj.Blog.Web.Host","ProjectName":"Wyj.Blog.Web.Host","CodeTemplates":[]},"WebCore":{"PType":9,"BasePath":"C:\\Users\\97953\\Desktop\\Wyj.Blog (1)\\5.5.0\\aspnet-core\\src\\Wyj.Blog.Web.Core","ProjectName":"Wyj.Blog.Web.Core","CodeTemplates":[]},"Portal":null,"SolutionNamespace":"Blog","CompanyNamespace":"Wyj.","CurrentProjectName":"Wyj.Blog.Core","CurrentSelectFilePath":"C:\\Users\\97953\\Desktop\\Wyj.Blog (1)\\5.5.0\\aspnet-core\\src\\Wyj.Blog.Core\\Blog\\Tag.cs","IsAbpZero":false,"SolutionPath":"C:\\Users\\97953\\Desktop\\Wyj.Blog (1)\\5.5.0\\aspnet-core"}